<?xml version="1.0" encoding="utf-8" ?><dwsync><file name="aboutlab.html" server="tusrras1.rs.tus.ac.jp" local="3795732572" remote="3795732633" Dst="-1" /><file name="access.html" server="tusrras1.rs.tus.ac.jp" local="3795732578" remote="3795732633" Dst="-1" /><file name="achievement.html" server="tusrras1.rs.tus.ac.jp" local="3795732584" remote="3795732633" Dst="-1" /><file name="index.html" server="tusrras1.rs.tus.ac.jp" local="3795732559" remote="3795732633" Dst="-1" /><file name="members.html" server="tusrras1.rs.tus.ac.jp" local="3795732594" remote="3795732633" Dst="-1" /><file name="past_news.html" server="tusrras1.rs.tus.ac.jp" local="3795732605" remote="3795732633" Dst="-1" /><file name="profile_kase.html" server="tusrras1.rs.tus.ac.jp" local="3795732617" remote="3795732633" Dst="-1" /><file name="README.md" server="tusrras1.rs.tus.ac.jp" local="3795516122" remote="3795579989" Dst="-1" /><file name="notes.txt" server="tusrras1.rs.tus.ac.jp" local="3794888253" remote="3794888253" Dst="-1" /></dwsync>